ipmaths/__init__.py
ipmaths/ipmaths.py
ipmaths/setup.py
ipmaths-0.1.1.dist-info/licenses/LICENSES/CC0-1.0.txt
ipmaths-0.1.1.dist-info/licenses/LICENSES/GPL-3.0-only.txt
ipmaths-0.1.1.dist-info/METADATA
ipmaths-0.1.1.dist-info/WHEEL
ipmaths-0.1.1.dist-info/top_level.txt
ipmaths-0.1.1.dist-info/RECORD
