Metadata-Version: 2.4
Name: ipmaths
Version: 0.1.1
Summary: A Python module that performs common IPv4 addressing calculations for network engineers.
Author-email: Ben Bonacci <ben@benbonacci.com>
License-Expression: GPL-3.0-only
Project-URL: Repository, https://code.benbonacci.com/ben/ipmaths
Project-URL: Documentation, https://code.benbonacci.com/ben/ipmaths/wiki
Project-URL: Issues, https://lists.benbonacci.com/ipmaths-bugs
Keywords: ip,internet,networking,calculator
Classifier: Development Status :: 3 - Alpha
Classifier: Environment :: Console
Classifier: Intended Audience :: Education
Classifier: Intended Audience :: Information Technology
Classifier: Programming Language :: Python :: 3
Classifier: Natural Language :: English
Classifier: Operating System :: OS Independent
Classifier: Topic :: Scientific/Engineering :: Mathematics
Classifier: Topic :: Utilities
Requires-Python: >=3.0
License-File: LICENSES/CC0-1.0.txt
License-File: LICENSES/GPL-3.0-only.txt
Dynamic: license-file
